iturtle/__init__.py
iturtle/frontend.py
iturtle/screen.py
iturtle/turtle.py
iturtle/utils.py
iturtle/version.py
iturtle/wrapper.py
iturtle/labextension/package.json
iturtle/labextension/static/162.5ce37aac0f822b8ef156.js
iturtle/labextension/static/367.75a693bbc420a614b24e.js
iturtle/labextension/static/480.60e006ee96e4624ac6cd.js
iturtle/labextension/static/534.bdc886a63d480aaff358.js
iturtle/labextension/static/568.6ab3f3b7eb02c1b8cc09.js
iturtle/labextension/static/908.03c10d4eef9726819b48.js
iturtle/labextension/static/remoteEntry.9337b8ec07fa10536a33.js
iturtle/labextension/static/style.js
iturtle/labextension/static/third-party-licenses.json
iturtle/nbextension/extension.js
iturtle/nbextension/index.js
iturtle/nbextension/index.js.LICENSE.txt
iturtle/nbextension/index.js.map
iturtle/tests/__init__.py
iturtle/tests/conftest.py
iturtle/tests/test_nbextension_path.py
iturtle/tests/test_widget.py
iturtle-1.0.16.data/data/etc/jupyter/nbconfig/notebook.d/iturtle.json
iturtle-1.0.16.data/data/share/jupyter/labextensions/iturtle/install.json
iturtle-1.0.16.data/data/share/jupyter/labextensions/iturtle/package.json
iturtle-1.0.16.data/data/share/jupyter/labextensions/iturtle/static/162.5ce37aac0f822b8ef156.js
iturtle-1.0.16.data/data/share/jupyter/labextensions/iturtle/static/367.75a693bbc420a614b24e.js
iturtle-1.0.16.data/data/share/jupyter/labextensions/iturtle/static/480.60e006ee96e4624ac6cd.js
iturtle-1.0.16.data/data/share/jupyter/labextensions/iturtle/static/534.bdc886a63d480aaff358.js
iturtle-1.0.16.data/data/share/jupyter/labextensions/iturtle/static/568.6ab3f3b7eb02c1b8cc09.js
iturtle-1.0.16.data/data/share/jupyter/labextensions/iturtle/static/908.03c10d4eef9726819b48.js
iturtle-1.0.16.data/data/share/jupyter/labextensions/iturtle/static/remoteEntry.9337b8ec07fa10536a33.js
iturtle-1.0.16.data/data/share/jupyter/labextensions/iturtle/static/style.js
iturtle-1.0.16.data/data/share/jupyter/labextensions/iturtle/static/third-party-licenses.json
iturtle-1.0.16.dist-info/licenses/LICENSE.txt
iturtle-1.0.16.dist-info/METADATA
iturtle-1.0.16.dist-info/WHEEL
iturtle-1.0.16.dist-info/top_level.txt
iturtle-1.0.16.dist-info/RECORD
